{
  "openapi": "3.0.0",
  "info": {
    "title": "divideLot",
    "version": "1.0"
  },
  "servers": [
    {
      "url": "{host}"
    }
  ],
  "paths": {
    "/divide/lot/{Contract Process ID}/{Lot Identifier}": {
      "post": {
        "summary": "divideLot",
        "operationId": "divideLot",
        "description": "",
        "parameters": [
          {
            "schema": {
              "type": "string"
            },
            "in": "header",
            "name": "Authorization Token ",
            "description": "Bearer {access_token}",
            "required": true
          },
          {
            "schema": {
              "type": "string"
            },
            "in": "header",
            "name": "Transaction ID",
            "description": "ID транзакции",
            "required": true
          },
          {
            "schema": {
              "type": "string"
            },
            "in": "header",
            "name": "Entity Token ",
            "description": "contract process токен",
            "required": true
          },
          {
            "schema": {
              "type": "string"
            },
            "in": "header",
            "name": "Content-Type",
            "description": "тип данных в теле запроса",
            "required": true
          }
        ],
        "requestBody": {
          "content": {
            "application/json": {
              "schema": {
                "description": "",
                "type": "object",
                "x-examples": {
                  "example-1": {
                    "tender": {
                      "lots": [
                        {
                          "id": "string",
                          "internalId": "string",
                          "title": "string",
                          "description": "string",
                          "value": {
                            "amount": 0,
                            "currency": "string"
                          },
                          "contractPeriod": {
                            "startDate": "2021-09-29T09:13:04.062Z",
                            "endDate": "2021-09-29T09:13:04.062Z"
                          },
                          "placeOfPerformance": {
                            "address": {
                              "streetAddress": "string",
                              "postalCode": "string",
                              "addressDetails": {
                                "country": {
                                  "id": "string",
                                  "description": "string",
                                  "scheme": "string"
                                },
                                "region": {
                                  "id": "string",
                                  "description": "string",
                                  "scheme": "string"
                                },
                                "locality": {
                                  "id": "string",
                                  "description": "string",
                                  "scheme": "string"
                                }
                              }
                            },
                            "description": "string"
                          },
                          "hasOptions": true,
                          "options": [
                            {
                              "description": "string",
                              "period": {
                                "durationInDays": 0,
                                "startDate": "2021-09-29T09:13:04.062Z",
                                "endDate": "2021-09-29T09:13:04.062Z",
                                "maxExtentDate": "2021-09-29T09:13:04.062Z"
                              }
                            }
                          ],
                          "hasRecurrence": true,
                          "recurrence": {
                            "dates": [
                              {
                                "startDate": "2021-09-29T09:13:04.062Z"
                              }
                            ],
                            "description": "string"
                          },
                          "hasRenewal": true,
                          "renewal": {
                            "description": "string",
                            "minimumRenewals": 0,
                            "maximumRenewals": 0,
                            "period": {
                              "durationInDays": 0,
                              "startDate": "2021-09-29T09:13:04.062Z",
                              "endDate": "2021-09-29T09:13:04.062Z",
                              "maxExtentDate": "2021-09-29T09:13:04.062Z"
                            }
                          }
                        }
                      ],
                      "items": [
                        {
                          "id": "string",
                          "relatedLot": "string"
                        }
                      ]
                    }
                  }
                },
                "properties": {
                  "tender": {
                    "type": "object",
                    "required": [
                      "lots",
                      "items"
                    ],
                    "properties": {
                      "lots": {
                        "type": "array",
                        "uniqueItems": true,
                        "minItems": 1,
                        "items": {
                          "type": "object",
                          "properties": {
                            "id": {
                              "type": "string",
                              "minLength": 1
                            },
                            "internalId": {
                              "type": "string",
                              "minLength": 1
                            },
                            "title": {
                              "type": "string",
                              "minLength": 1
                            },
                            "description": {
                              "type": "string",
                              "minLength": 1
                            },
                            "value": {
                              "type": "object",
                              "required": [
                                "amount",
                                "currency"
                              ],
                              "properties": {
                                "amount": {
                                  "type": "number"
                                },
                                "currency": {
                                  "type": "string",
                                  "minLength": 1
                                }
                              }
                            },
                            "contractPeriod": {
                              "type": "object",
                              "required": [
                                "startDate",
                                "endDate"
                              ],
                              "properties": {
                                "startDate": {
                                  "type": "string",
                                  "minLength": 1,
                                  "format": "date-time"
                                },
                                "endDate": {
                                  "type": "string",
                                  "minLength": 1,
                                  "format": "date-time"
                                }
                              }
                            },
                            "placeOfPerformance": {
                              "type": "object",
                              "required": [
                                "address",
                                "description"
                              ],
                              "properties": {
                                "address": {
                                  "type": "object",
                                  "required": [
                                    "streetAddress",
                                    "addressDetails"
                                  ],
                                  "properties": {
                                    "streetAddress": {
                                      "type": "string",
                                      "minLength": 1
                                    },
                                    "postalCode": {
                                      "type": "string",
                                      "minLength": 1
                                    },
                                    "addressDetails": {
                                      "type": "object",
                                      "required": [
                                        "country",
                                        "region",
                                        "locality"
                                      ],
                                      "properties": {
                                        "country": {
                                          "type": "object",
                                          "required": [
                                            "id",
                                            "description",
                                            "scheme"
                                          ],
                                          "properties": {
                                            "id": {
                                              "type": "string",
                                              "minLength": 1
                                            },
                                            "description": {
                                              "type": "string",
                                              "minLength": 1
                                            },
                                            "scheme": {
                                              "type": "string",
                                              "minLength": 1
                                            }
                                          }
                                        },
                                        "region": {
                                          "type": "object",
                                          "required": [
                                            "id",
                                            "description",
                                            "scheme"
                                          ],
                                          "properties": {
                                            "id": {
                                              "type": "string",
                                              "minLength": 1
                                            },
                                            "description": {
                                              "type": "string",
                                              "minLength": 1
                                            },
                                            "scheme": {
                                              "type": "string",
                                              "minLength": 1
                                            }
                                          }
                                        },
                                        "locality": {
                                          "type": "object",
                                          "required": [
                                            "id",
                                            "description",
                                            "scheme"
                                          ],
                                          "properties": {
                                            "id": {
                                              "type": "string",
                                              "minLength": 1
                                            },
                                            "description": {
                                              "type": "string",
                                              "minLength": 1
                                            },
                                            "scheme": {
                                              "type": "string",
                                              "minLength": 1
                                            }
                                          }
                                        }
                                      }
                                    }
                                  }
                                },
                                "description": {
                                  "type": "string",
                                  "minLength": 1
                                }
                              }
                            },
                            "hasOptions": {
                              "type": "boolean"
                            },
                            "options": {
                              "type": "array",
                              "uniqueItems": true,
                              "minItems": 1,
                              "items": {
                                "type": "object",
                                "properties": {
                                  "description": {
                                    "type": "string",
                                    "minLength": 1
                                  },
                                  "period": {
                                    "type": "object",
                                    "properties": {
                                      "durationInDays": {
                                        "type": "number"
                                      },
                                      "startDate": {
                                        "type": "string",
                                        "minLength": 1,
                                        "format": "date-time"
                                      },
                                      "endDate": {
                                        "type": "string",
                                        "minLength": 1,
                                        "format": "date-time"
                                      },
                                      "maxExtentDate": {
                                        "type": "string",
                                        "minLength": 1
                                      }
                                    }
                                  }
                                }
                              }
                            },
                            "hasRecurrence": {
                              "type": "boolean"
                            },
                            "recurrence": {
                              "type": "object",
                              "properties": {
                                "dates": {
                                  "type": "array",
                                  "uniqueItems": true,
                                  "minItems": 1,
                                  "items": {
                                    "type": "object",
                                    "properties": {
                                      "startDate": {
                                        "type": "string",
                                        "minLength": 1
                                      }
                                    },
                                    "required": [
                                      "startDate"
                                    ]
                                  }
                                },
                                "description": {
                                  "type": "string",
                                  "minLength": 1
                                }
                              }
                            },
                            "hasRenewal": {
                              "type": "boolean"
                            },
                            "renewal": {
                              "type": "object",
                              "properties": {
                                "description": {
                                  "type": "string",
                                  "minLength": 1
                                },
                                "minimumRenewals": {
                                  "type": "number"
                                },
                                "maximumRenewals": {
                                  "type": "number"
                                },
                                "period": {
                                  "type": "object",
                                  "properties": {
                                    "durationInDays": {
                                      "type": "number"
                                    },
                                    "startDate": {
                                      "type": "string",
                                      "minLength": 1,
                                      "format": "date-time"
                                    },
                                    "endDate": {
                                      "type": "string",
                                      "minLength": 1,
                                      "format": "date-time"
                                    },
                                    "maxExtentDate": {
                                      "type": "string",
                                      "minLength": 1
                                    }
                                  }
                                }
                              }
                            }
                          },
                          "required": [
                            "id",
                            "internalId",
                            "title",
                            "description",
                            "value",
                            "contractPeriod",
                            "placeOfPerformance"
                          ]
                        }
                      },
                      "items": {
                        "type": "array",
                        "uniqueItems": true,
                        "minItems": 1,
                        "items": {
                          "type": "object",
                          "properties": {
                            "id": {
                              "type": "string",
                              "minLength": 1
                            },
                            "relatedLot": {
                              "type": "string",
                              "minLength": 1
                            }
                          },
                          "required": [
                            "id",
                            "relatedLot"
                          ]
                        }
                      }
                    }
                  }
                },
                "required": [
                  "tender"
                ]
              }
            }
          }
        },
        "responses": {
          "200": {
            "description": "OK",
            "content": {
              "application/json": {
                "schema": {
                  "description": "",
                  "type": "object",
                  "x-examples": {
                    "example-1": {
                      "tender": {
                        "lots": [
                          {
                            "id": "string",
                            "internalId": "string",
                            "title": "string",
                            "description": "string",
                            "value": {
                              "amount": 0,
                              "currency": "string"
                            },
                            "contractPeriod": {
                              "startDate": "2022-01-20T12:45:18.475Z",
                              "endDate": "2022-01-20T12:45:18.475Z"
                            },
                            "placeOfPerformance": {
                              "address": {
                                "streetAddress": "string",
                                "postalCode": "string",
                                "addressDetails": {
                                  "country": {
                                    "id": "string",
                                    "description": "string",
                                    "scheme": "string",
                                    "uri": "string"
                                  },
                                  "region": {
                                    "id": "string",
                                    "description": "string",
                                    "scheme": "string",
                                    "uri": "string"
                                  },
                                  "locality": {
                                    "id": "string",
                                    "description": "string",
                                    "scheme": "string",
                                    "uri": "string"
                                  }
                                }
                              },
                              "description": "string"
                            },
                            "status": "cancelled",
                            "statusDetails": "empty",
                            "hasOptions": true,
                            "options": [
                              {
                                "description": "string",
                                "period": {
                                  "durationInDays": 0,
                                  "startDate": "2022-01-20T12:45:18.475Z",
                                  "endDate": "2022-01-20T12:45:18.475Z",
                                  "maxExtentDate": "2022-01-20T12:45:18.475Z"
                                }
                              }
                            ],
                            "hasRecurrence": true,
                            "recurrence": {
                              "dates": [
                                {
                                  "startDate": "2022-01-20T12:45:18.475Z"
                                }
                              ],
                              "description": "string"
                            },
                            "hasRenewal": true,
                            "renewal": {
                              "description": "string",
                              "minimumRenewals": 0,
                              "maximumRenewals": 0,
                              "period": {
                                "durationInDays": 0,
                                "startDate": "2022-01-20T12:45:18.475Z",
                                "endDate": "2022-01-20T12:45:18.475Z",
                                "maxExtentDate": "2022-01-20T12:45:18.475Z"
                              }
                            }
                          }
                        ],
                        "items": [
                          {
                            "id": "string",
                            "internalId": "string",
                            "classification": {
                              "id": "string",
                              "scheme": "string",
                              "description": "string"
                            },
                            "additionalClassifications": [
                              {
                                "id": "string",
                                "scheme": "string",
                                "description": "string"
                              }
                            ],
                            "quantity": 0,
                            "unit": {
                              "id": "string",
                              "name": "string"
                            },
                            "description": "string",
                            "relatedLot": "string"
                          }
                        ]
                      }
                    }
                  },
                  "properties": {
                    "tender": {
                      "type": "object",
                      "required": [
                        "lots",
                        "items"
                      ],
                      "properties": {
                        "lots": {
                          "type": "array",
                          "items": {
                            "type": "object",
                            "properties": {
                              "id": {
                                "type": "string"
                              },
                              "internalId": {
                                "type": "string"
                              },
                              "title": {
                                "type": "string"
                              },
                              "description": {
                                "type": "string"
                              },
                              "status": {
                                "type": "string",
                                "enum": [
                                  "planning",
                                  "active",
                                  "complete",
                                  "unsuccessful",
                                  "cancelled"
                                ]
                              },
                              "statusDetails": {
                                "type": "string",
                                "enum": [
                                  "empty",
                                  "awarded"
                                ]
                              },
                              "value": {
                                "type": "object",
                                "required": [
                                  "amount",
                                  "currency"
                                ],
                                "properties": {
                                  "amount": {
                                    "type": "number"
                                  },
                                  "currency": {
                                    "type": "string"
                                  }
                                }
                              },
                              "contractPeriod": {
                                "type": "object",
                                "required": [
                                  "startDate",
                                  "endDate"
                                ],
                                "properties": {
                                  "startDate": {
                                    "type": "string",
                                    "format": "date-time"
                                  },
                                  "endDate": {
                                    "type": "string",
                                    "format": "date-time"
                                  }
                                }
                              },
                              "placeOfPerformance": {
                                "type": "object",
                                "required": [
                                  "address"
                                ],
                                "properties": {
                                  "address": {
                                    "type": "object",
                                    "required": [
                                      "streetAddress",
                                      "addressDetails"
                                    ],
                                    "properties": {
                                      "streetAddress": {
                                        "type": "string"
                                      },
                                      "postalCode": {
                                        "type": "string"
                                      },
                                      "addressDetails": {
                                        "type": "object",
                                        "required": [
                                          "country",
                                          "region",
                                          "locality"
                                        ],
                                        "properties": {
                                          "country": {
                                            "type": "object",
                                            "required": [
                                              "scheme",
                                              "id",
                                              "description",
                                              "uri"
                                            ],
                                            "properties": {
                                              "scheme": {
                                                "type": "string"
                                              },
                                              "id": {
                                                "type": "string"
                                              },
                                              "description": {
                                                "type": "string"
                                              },
                                              "uri": {
                                                "type": "string",
                                                "format": "uri"
                                              }
                                            }
                                          },
                                          "region": {
                                            "type": "object",
                                            "required": [
                                              "scheme",
                                              "id",
                                              "description",
                                              "uri"
                                            ],
                                            "properties": {
                                              "scheme": {
                                                "type": "string"
                                              },
                                              "id": {
                                                "type": "string"
                                              },
                                              "description": {
                                                "type": "string"
                                              },
                                              "uri": {
                                                "type": "string",
                                                "format": "uri"
                                              }
                                            }
                                          },
                                          "locality": {
                                            "type": "object",
                                            "required": [
                                              "scheme",
                                              "id",
                                              "description"
                                            ],
                                            "properties": {
                                              "scheme": {
                                                "type": "string"
                                              },
                                              "id": {
                                                "type": "string"
                                              },
                                              "description": {
                                                "type": "string"
                                              },
                                              "uri": {
                                                "type": "string",
                                                "format": "uri"
                                              }
                                            }
                                          }
                                        }
                                      }
                                    }
                                  },
                                  "description": {
                                    "type": "string"
                                  }
                                }
                              },
                              "hasOptions": {
                                "type": "boolean"
                              },
                              "options": {
                                "type": "array",
                                "items": {
                                  "type": "object",
                                  "properties": {
                                    "description": {
                                      "type": "string"
                                    },
                                    "period": {
                                      "type": "object",
                                      "properties": {
                                        "durationInDays": {
                                          "type": "number"
                                        },
                                        "startDate": {
                                          "type": "string",
                                          "format": "date-time"
                                        },
                                        "endDate": {
                                          "type": "string",
                                          "format": "date-time"
                                        },
                                        "maxExtentDate": {
                                          "type": "string",
                                          "format": "date-time"
                                        }
                                      }
                                    }
                                  }
                                }
                              },
                              "hasRecurrence": {
                                "type": "boolean"
                              },
                              "recurrence": {
                                "type": "object",
                                "properties": {
                                  "dates": {
                                    "type": "array",
                                    "items": {
                                      "type": "object",
                                      "properties": {
                                        "startDate": {
                                          "type": "string",
                                          "format": "date-time"
                                        }
                                      }
                                    }
                                  },
                                  "description": {
                                    "type": "string"
                                  }
                                }
                              },
                              "hasRenewal": {
                                "type": "boolean"
                              },
                              "renewal": {
                                "type": "object",
                                "properties": {
                                  "description": {
                                    "type": "string"
                                  },
                                  "minimumRenewals": {
                                    "type": "number"
                                  },
                                  "maximumRenewals": {
                                    "type": "number"
                                  },
                                  "period": {
                                    "type": "object",
                                    "properties": {
                                      "durationInDays": {
                                        "type": "number"
                                      },
                                      "startDate": {
                                        "type": "string",
                                        "format": "date-time"
                                      },
                                      "endDate": {
                                        "type": "string",
                                        "format": "date-time"
                                      },
                                      "maxExtentDate": {
                                        "type": "string",
                                        "format": "date-time"
                                      }
                                    }
                                  }
                                }
                              }
                            },
                            "required": [
                              "id",
                              "title",
                              "description",
                              "status",
                              "statusDetails",
                              "value",
                              "contractPeriod",
                              "placeOfPerformance",
                              "hasOptions",
                              "hasRecurrence",
                              "hasRenewal"
                            ]
                          }
                        },
                        "items": {
                          "type": "array",
                          "items": {
                            "type": "object",
                            "properties": {
                              "id": {
                                "type": "string"
                              },
                              "internalId": {
                                "type": "string"
                              },
                              "classification": {
                                "type": "object",
                                "required": [
                                  "scheme",
                                  "description",
                                  "id"
                                ],
                                "properties": {
                                  "scheme": {
                                    "type": "string"
                                  },
                                  "description": {
                                    "type": "string"
                                  },
                                  "id": {
                                    "type": "string"
                                  }
                                }
                              },
                              "additionalClassifications": {
                                "type": "array",
                                "items": {
                                  "type": "object",
                                  "properties": {
                                    "scheme": {
                                      "type": "string",
                                      "description": "The scheme or codelist from which the classification code is taken. "
                                    },
                                    "description": {
                                      "type": "string",
                                      "description": "A textual description or title for the classification code."
                                    },
                                    "id": {
                                      "type": "string",
                                      "description": "The classification code taken from the scheme."
                                    }
                                  },
                                  "required": [
                                    "scheme",
                                    "description",
                                    "id"
                                  ]
                                }
                              },
                              "quantity": {
                                "type": "number"
                              },
                              "unit": {
                                "type": "object",
                                "required": [
                                  "id",
                                  "name"
                                ],
                                "properties": {
                                  "id": {
                                    "type": "string"
                                  },
                                  "name": {
                                    "type": "string"
                                  }
                                }
                              },
                              "description": {
                                "type": "string"
                              },
                              "relatedLot": {
                                "type": "string"
                              }
                            },
                            "required": [
                              "id",
                              "classification",
                              "quantity",
                              "unit",
                              "description",
                              "relatedLot"
                            ]
                          }
                        }
                      }
                    }
                  },
                  "required": [
                    "tender"
                  ]
                }
              }
            }
          }
        }
      },
      "parameters": [
        {
          "schema": {
            "type": "string"
          },
          "name": "Contract Process ID",
          "in": "path",
          "required": true,
          "description": "cpid/ocid "
        },
        {
          "schema": {
            "type": "string"
          },
          "name": "Lot Identifier",
          "in": "path",
          "required": true,
          "description": "id делимого лота"
        }
      ]
    }
  },
  "components": {
    "schemas": {}
  }
}